[{"country": "Kenya", "bounding_box": [33.909709930419915, -4.705271349577345, 41.906055450439446, 5.414106845855666], "region": ["BARINGO", "BOMET", "BUNGOMA", "BUSIA", "ELGEYO_MARAKWET", "GARISSA", "HOMA BAY", "ISIOLO", "KAJIADO", "KAKAMEGA", "KERICHO", "KIRINYAGA", "KISII", "KISUMU", "KITUI", "KWALE", "LAIKIPIA", "LAMU", "MANDERA", "MARSABIT", "MERU", "MIGORI", "MURANG'A", "NAKURU", "NANDI", "NAROK", "NYAMIRA", "NYANDARUA", "NYERI", "SAMBURU", "SIAYA", "TAITA_TAVETA", "TANA RIVER", "THARAKA-NITHI", "TRANS-NZOIA", "TURKANA", "UASIN GISHU", "VIHIGA", "WAJIR", "WEST POKOT", "MOMBASA", "KILIFI", "EMBU", "MAKUENI", "NAIROBI", "MACHAKOS", "KIAMBU"]}, {"country": "South Sudan", "bounding_box": [23.440849, 3.488987, 35.948997, 12.236389], "region": ["North Bahr-al-Ghazal", "Lakes", "West Equatoria", "Central Equatoria", "Upper Nile", "Jungoli", "Unity", "Warap", "West Bahr-al-Ghazal", "East Equatoria"]}, {"country": "Rwanda", "bounding_box": [28.861731, -2.84023, 30.899747, -1.047167], "region": ["Southern", "Western", "Eastern", "Northern", "Kigali City"]}, {"country": "Burundi", "bounding_box": [29.000345, -4.470001, 30.850906, -2.30907], "region": ["Cankuzo", "Karuzi", "Rutana", "Ruyigi", "Bubanza", "Bururi", "Cibitoke", "Gitega", "Kayanza", "Makamba", "Ngozi", "Kirundo", "Muyinga", "Bujumbura Mairie", "Muramvya", "Bujumbura Rural", "Mwaro", "Rumonge"]}, {"country": "Djibouti", "bounding_box": [41.759722, 10.931944, 43.444527, 12.713697], "region": ["Ali Sabieh", "Djibouti", "Arta", "Dikhil", "Obock", "Tadjourah"]}, {"country": "Eritrea", "bounding_box": [36.433348, 12.387868, 43.137048, 18.020414], "region": ["Gash Barka", "Debub", "Maekel", "Debubawi Keyih Bahri", "Central", "Anseba"]}, {"country": "Ethiopia", "bounding_box": [32.99993896484375, 3.322098970413265, 47.98617935180673, 14.899957656860337], "region": ["Addis Ababa", "Afar", "Amhara", "Benshangul-Gumaz", "Dire Dawa", "Gambela Peoples", "Harari People", "Oromia", "Somali", "Southern Nations, Nationalities and Peoples", "Tigray"]}, {"country": "Sudan", "bounding_box": [21.814939, 9.347221, 38.581341, 23.14827], "region": ["Blue Nile", "Red Sea", "Southern Darfur", "Eastern Darfur", "Western Darfur", "Central Darfur", "Khartoum", "Gezira", "Gedarif", "River Nile", "Northern", "White Nile", "Sennar", "North Darfur", "South Kordufan", "North Kordufan", "Kassala", "West Kordofan"]}, {"country": "Tanzania", "bounding_box": [29.589529, -11.762349, 40.444735, -0.983143], "region": ["Mbeya", "Rukwa", "Zanzibar South and Central", "Mwanza", "Shinyanga", "Tabora", "Kagera", "Kigoma", "Dar-es-Salaam", "Morogoro", "Kaskazini-Pemba", "Kusini-Pemba", "Pwani", "Kaskazini-Unguja", "Zanzibar West", "Dodoma", "Iringa", "Lindi", "Mtwara", "Ruvuma", "Singida", "Arusha", "Manyara", "Kilimanjaro", "Mara", "Tanga", "Katavi", "Simiyu", "Geita", "Njombe"]}, {"country": "Somalia", "bounding_box": [40.99431700000008, -1.664897400999962, 51.413032532000045, 11.985202789000027], "region": ["Somalia"]}, {"country": "Uganda", "bounding_box": [29.57149887084961, -1.4788700342178345, 35.00027465820311, 4.234466075897185], "region": ["Uganda"]}]